rr/__init__.py
rr/approx/LICENSE
rr/approx/VERSION
rr/approx/__init__.py
rr.approx-0.1.2.dist-info/DESCRIPTION.rst
rr.approx-0.1.2.dist-info/METADATA
rr.approx-0.1.2.dist-info/RECORD
rr.approx-0.1.2.dist-info/WHEEL
rr.approx-0.1.2.dist-info/metadata.json
rr.approx-0.1.2.dist-info/top_level.txt
