Metadata-Version: 2.0
Name: rr.approx
Version: 0.1.2
Summary: A simple module for approximate floating point arithmetic.
Home-page: https://github.com/2xR/rr.approx
Author: Rui Jorge Rei
Author-email: rui.jorge.rei@googlemail.com
License: MIT
Platform: UNKNOWN
Classifier: Development Status :: 3 - Alpha
Classifier: License :: OSI Approved :: MIT License
Classifier: Programming Language :: Python :: 2
Classifier: Programming Language :: Python :: 2.7
